README.rst
setup.py
exemelopy/__init__.py
exemelopy/__version__.py
exemelopy.egg-info/PKG-INFO
exemelopy.egg-info/SOURCES.txt
exemelopy.egg-info/dependency_links.txt
exemelopy.egg-info/pbr.json
exemelopy.egg-info/requires.txt
exemelopy.egg-info/top_level.txt