Metadata-Version: 1.1
Name: exemelopy
Version: 0.0.9
Summary: exemelopy is a tool for building XML from native Python data-types, similiar to the json/simplejson modules
Home-page: https://github.com/OldhamMade/exemelopy
Author: Phillip B Oldham
Author-email: phillip.oldham@gmail.com
License: UNKNOWN
Download-URL: https://github.com/OldhamMade/exemelopy/archive/master.zip
Platform: UNKNOWN
